nsface_match/__init__.py
nsface_match/face/__init__.py
nsface_match/face/common.py
nsface_match/face/__pycache__/__init__.cpython-38.pyc
nsface_match/face/__pycache__/common.cpython-38.pyc
nsface_match/model/__init__.py
nsface_match/model/load_arcface.py
nsface_match/model/load_onnx.py
nsface_match/model/load_trt.py
nsface_match/model/load_vino.py
nsface_match/model/__pycache__/__init__.cpython-38.pyc
nsface_match/model/__pycache__/load_arcface.cpython-38.pyc
nsface_match/model/__pycache__/load_onnx.cpython-38.pyc
nsface_match/model/__pycache__/load_trt.cpython-38.pyc
nsface_match/model/__pycache__/load_vino.cpython-38.pyc
nsface_match_python-0.0.14.dist-info/METADATA
nsface_match_python-0.0.14.dist-info/WHEEL
nsface_match_python-0.0.14.dist-info/top_level.txt
nsface_match_python-0.0.14.dist-info/RECORD
